my_second_ph3_package/__init__.py
my_second_ph3_package/my_second_ph3_package.py
my_second_ph3_package/sub_package_1/__init__.py
my_second_ph3_package/sub_package_1/my_class_1.py
my_second_ph3_package/sub_package_2/__init__.py
my_second_ph3_package/sub_package_2/my_class_2.py
my_second_ph3_package/sub_package_2/my_class_3.py
my_second_ph3_package-0.1.0.dist-info/LICENSE
my_second_ph3_package-0.1.0.dist-info/METADATA
my_second_ph3_package-0.1.0.dist-info/WHEEL
my_second_ph3_package-0.1.0.dist-info/RECORD
