Metadata-Version: 2.1
Name: my-second-ph3-package
Version: 0.1.0
Summary: This time it will work perfectly!
Home-page: https://github.com/balouf/my-second-ph3-package
Author: Fabien Mathieu
Author-email: loufab@gmail.com
Requires-Python: >=3.9,<4.0
Classifier: Programming Language :: Python :: 3
Classifier: Programming Language :: Python :: 3.9
Classifier: Programming Language :: Python :: 3.10
Classifier: Programming Language :: Python :: 3.11
Project-URL: Documentation, https://balouf.github.io/my-second-ph3-package
Project-URL: Repository, https://github.com/balouf/my-second-ph3-package
